acq400_hapi/__init__.py
acq400_hapi/acq400.py
acq400_hapi/acq400_ui.py
acq400_hapi/acq400_uut_handler.py
acq400_hapi/afhba404.py
acq400_hapi/agilent33210.py
acq400_hapi/awg_data.py
acq400_hapi/cleanup.py
acq400_hapi/debug.py
acq400_hapi/intSI.py
acq400_hapi/intSIAction.py
acq400_hapi/netclient.py
acq400_hapi/rad_dds.py
acq400_hapi/shotcontrol.py
acq400_hapi/utils.py
acq400_hapi-2.9.4.dist-info/LICENSE
acq400_hapi-2.9.4.dist-info/METADATA
acq400_hapi-2.9.4.dist-info/WHEEL
acq400_hapi-2.9.4.dist-info/top_level.txt
acq400_hapi-2.9.4.dist-info/RECORD
