Metadata-Version: 2.1
Name: acq400-hapi
Version: 2.9.4
Summary: A python package for connection ACQ400 series D-TACQ products.
Home-page: https://github.com/D-TACQ/acq400_hapi
Author: UNKNOWN
Author-email: UNKNOWN
License: UNKNOWN
Keywords: D-TACQ
Platform: UNKNOWN
Classifier: Development Status :: 5 - Production/Stable
Classifier: Intended Audience :: Developers
Classifier: Topic :: Software Development :: Build Tools
Classifier: Programming Language :: Python :: 2
Classifier: Programming Language :: Python :: 2.7
Requires-Dist: future
